metamodel/__init__.py
metamodel/error.py
metamodel/metamodel.py
metamodel/statemachine.py
pflow_metamodel-0.3.0.dist-info/LICENSE
pflow_metamodel-0.3.0.dist-info/METADATA
pflow_metamodel-0.3.0.dist-info/WHEEL
pflow_metamodel-0.3.0.dist-info/top_level.txt
pflow_metamodel-0.3.0.dist-info/RECORD
